pydll_injector/__init__.py
pydll_injector/cli.py
pydll_injector/constants.py
pydll_injector/injectors.py
pydll_injector/models.py
pydll_injector/native.py
pydll_injector/process.py
pydll_injector/utils.py
pydll_injector-0.1.2.dist-info/METADATA
pydll_injector-0.1.2.dist-info/WHEEL
pydll_injector-0.1.2.dist-info/entry_points.txt
pydll_injector-0.1.2.dist-info/licenses/LICENSE
pydll_injector-0.1.2.dist-info/RECORD
