Metadata-Version: 2.4
Name: pydll_injector
Version: 0.1.2
Summary: Python DLL injector for Windows.
License-File: LICENSE
Requires-Python: >=3.9
Provides-Extra: cli
Requires-Dist: pydantic; extra == 'cli'
Requires-Dist: tomli; extra == 'cli'
